mocharts/__init__.py
mocharts/render/utils.cpython-39-x86_64-linux-gnu.so
mocharts/render/renderer.cpython-39-x86_64-linux-gnu.so
mocharts/render/__init__.py
mocharts/render/frontend/js_function.cpython-39-x86_64-linux-gnu.so
mocharts/render/frontend/html_template.cpython-39-x86_64-linux-gnu.so
mocharts/render/frontend/__init__.py
mocharts/render/frontend/dist/css/inner_html.css
mocharts/render/frontend/dist/js/echarts-gl.min.js
mocharts/render/frontend/dist/js/echarts_general_plugin.js
mocharts/render/frontend/dist/js/echarts_inner_plugin.js
mocharts/render/frontend/dist/js/fastly.jsdelivr.net_npm_dat.gui@0.6.5_build_dat.gui.min.js
mocharts/render/frontend/dist/js/echarts.min.js
mocharts/render/frontend/dist/js/utils.js
mocharts/render/frontend/dist/js/echarts_plugin.js
mocharts/render/frontend/dist/js/echarts-wordcloud.min.js
mocharts/render/frontend/dist/static/popup_icon.png
mocharts/render/local_server/utils.cpython-39-x86_64-linux-gnu.so
mocharts/render/local_server/base.cpython-39-x86_64-linux-gnu.so
mocharts/render/local_server/local_storage.cpython-39-x86_64-linux-gnu.so
mocharts/render/local_server/local_resource_container.cpython-39-x86_64-linux-gnu.so
mocharts/render/local_server/__init__.py
mocharts/render/local_server/local_endpoints/js2py.cpython-39-x86_64-linux-gnu.so
mocharts/render/local_server/local_endpoints/general_endpoint.cpython-39-x86_64-linux-gnu.so
mocharts/render/local_server/local_endpoints/__init__.py
mocharts/calculation/utils.cpython-39-x86_64-linux-gnu.so
mocharts/calculation/sampler.cpython-39-x86_64-linux-gnu.so
mocharts/calculation/sns_utils.cpython-39-x86_64-linux-gnu.so
mocharts/calculation/__init__.py
mocharts/plot/container.cpython-39-x86_64-linux-gnu.so
mocharts/plot/utils.cpython-39-x86_64-linux-gnu.so
mocharts/plot/config.cpython-39-x86_64-linux-gnu.so
mocharts/plot/__init__.py
mocharts/plot/src/func.cpython-39-x86_64-linux-gnu.so
mocharts/plot/src/__init__.py
MoCharts-1.0.3.dist-info/METADATA
MoCharts-1.0.3.dist-info/WHEEL
MoCharts-1.0.3.dist-info/top_level.txt
MoCharts-1.0.3.dist-info/RECORD
