Metadata-Version: 2.1
Name: MoCharts
Version: 1.0.3
Summary: An interactive data visualization package in Python.
Author: Modeva
License: Apache
Classifier: Programming Language :: Python :: 3.9
Classifier: Programming Language :: Python :: 3.10
Classifier: Programming Language :: Python :: 3.11
Classifier: Programming Language :: Python :: 3.12
Classifier: License :: OSI Approved :: Apache Software License
Requires-Dist: ipython>=7.12.0
Requires-Dist: uvicorn
Requires-Dist: fastapi
Requires-Dist: webdriver-manager>=4.0.2
Requires-Dist: selenium>=4.19.0
Requires-Dist: matplotlib
Requires-Dist: networkx
Requires-Dist: requests
Requires-Dist: numpy>=1.21.4
Requires-Dist: pandas>=1.3.5
Requires-Dist: scipy>=1.5.3
Requires-Dist: typer<0.10.0
Requires-Dist: packaging>=20.5
